[
    {
        "qid":"0000918-1",
        "qtype":"information",
        "question":"O que \u00e9 (s\u00e3o) pequena neuropatia de fibras?",
        "answer":"A neuropatia por fibras pequenas \u00e9 uma condi\u00e7\u00e3o caracterizada por ataques de dor graves que normalmente come\u00e7am nos p\u00e9s ou nas m\u00e3os. Quando uma pessoa envelhece, os ataques de dor podem afetar outras regi\u00f5es. Algumas pessoas inicialmente experimentam uma dor mais generalizada, do corpo inteiro. Os ataques geralmente consistem em dor descrita como esfaqueamento ou queimadura, ou sensa\u00e7\u00f5es cut\u00e2neas anormais como formigueiro ou comich\u00e3o. Em alguns indiv\u00edduos, a dor \u00e9 mais grave durante o repouso ou \u00e0 noite. Os sinais e sintomas da neuropatia por fibras pequenas geralmente come\u00e7am na adolesc\u00eancia at\u00e9 o meio da adultez. Indiv\u00edduos com pequena neuropatia por fibras n\u00e3o podem sentir dor que est\u00e1 concentrada em uma \u00e1rea muito pequena, como o pinto de um alfinete. No entanto, eles t\u00eam uma sensibilidade aumentada \u00e0 dor em geral (hiperalgesia) e sentem dor por estimula\u00e7\u00e3o que normalmente n\u00e3o causa dor (hipoestesia). As pessoas afetadas por esta condi\u00e7\u00e3o tamb\u00e9m podem ter uma capacidade reduzida de diferenciar entre quente e frio. No entanto, em alguns indiv\u00edduos, os ataques de dor s\u00e3o provocados por gatilhos frios ou quentes. Alguns indiv\u00edduos afetados t\u00eam problemas urin\u00e1rios ou intestinais, epis\u00f3dios de batimento card\u00edaco r\u00e1pido (palpita\u00e7\u00f5es), olhos secos ou boca, ou sudorese anormal. Eles tamb\u00e9m podem sentir uma queda acentuada na press\u00e3o arterial em p\u00e9 (hipotens\u00e3o ortost\u00e1tica), que pode causar tonturas, vis\u00e3o borrada, ou desmaio. A neuropatia por fibras pequenas \u00e9 considerada uma forma de neuropatia perif\u00e9rica porque afeta o sistema nervoso perif\u00e9rico, que liga o c\u00e9rebro e a medula espinhal aos m\u00fasculos e \u00e0s c\u00e9lulas que detectam sensa\u00e7\u00f5es como toque, cheiro e dor."
    },
    {
        "qid":"0000918-2",
        "qtype":"frequency",
        "question":"Quantas pessoas s\u00e3o afetadas pela neuropatia por fibras pequenas?",
        "answer":"A preval\u00eancia de neuropatia por fibras pequenas \u00e9 desconhecida."
    },
    {
        "qid":"0000918-3",
        "qtype":"genetic changes",
        "question":"Quais s\u00e3o as altera\u00e7\u00f5es gen\u00e9ticas relacionadas \u00e0 neuropatia por fibras pequenas?",
        "answer":"Muta\u00e7\u00f5es no gene SCN9A ou SCN10A podem causar neuropatia por fibras pequenas. Esses genes fornecem instru\u00e7\u00f5es para fazer pe\u00e7as (as subunidades alfa) de canais de s\u00f3dio. O gene SCN9A instrui a produ\u00e7\u00e3o da subunidade alfa para o canal de s\u00f3dio NaV1.7 e o gene SCN10A instrui a produ\u00e7\u00e3o da subunidade alfa para o canal de s\u00f3dio NaV1.8. Canais de s\u00f3dio transportam \u00e1tomos de s\u00f3dio carregados positivamente (ions de s\u00f3dio) para as c\u00e9lulas e desempenham um papel fundamental na capacidade de uma c\u00e9lula para gerar e transmitir sinais el\u00e9tricos. Os canais de s\u00f3dio NaV1.7 e NaV1.8 s\u00e3o encontrados em c\u00e9lulas nervosas chamadas nociceptores que transmitem sinais de dor para a medula espinhal e o c\u00e9rebro. As muta\u00e7\u00f5es do gene SCN9A que causam neuropatia de fibras pequenas resultam em canais de s\u00f3dio NaV1.7 que n\u00e3o se fecham completamente quando o canal est\u00e1 desligado. Muitas muta\u00e7\u00f5es do gene SCN10A resultam em canais de s\u00f3dio NaV1.8 que se abrem mais facilmente do que o normal. Os canais alterados permitem que os \u00edons de s\u00f3dio fluam anormalmente para os nociceptores. Este aumento de \u00edons de s\u00f3dio aumenta a transmiss\u00e3o de sinais de dor, fazendo com que os indiv\u00edduos sejam mais sens\u00edveis \u00e0 estimula\u00e7\u00e3o que de outra forma n\u00e3o causaria dor. Nesta condi\u00e7\u00e3o, as pequenas fibras que se estendem dos nociceptores atrav\u00e9s dos quais os sinais de dor s\u00e3o transmitidos (\u00e1xons) degeneram ao longo do tempo. A causa dessa degenera\u00e7\u00e3o \u00e9 desconhecida, mas provavelmente explica sinais e sintomas como a perda de diferencia\u00e7\u00e3o de temperatura e sensa\u00e7\u00e3o de pinpick. A combina\u00e7\u00e3o de sinaliza\u00e7\u00e3o de dor aumentada e degenera\u00e7\u00e3o de fibras transmissoras de dor leva a uma condi\u00e7\u00e3o vari\u00e1vel com sinais e sintomas que podem mudar ao longo do tempo. Muta\u00e7\u00f5es do gene SCN9A foram encontradas em aproximadamente 30% dos indiv\u00edduos com neuropatia por fibras pequenas; muta\u00e7\u00f5es do gene SCN10A s\u00e3o respons\u00e1veis por cerca de 5% dos casos. Em alguns casos, outras condi\u00e7\u00f5es de sa\u00fade causam esse transtorno. Diabetes mellitus e toler\u00e2ncia \u00e0 glicose prejudicada s\u00e3o as doen\u00e7as mais comuns que levam a este dist\u00farbio, com 6 a 50% dos diab\u00e9ticos ou pr\u00e9-diab\u00e9ticos desenvolvendo pequena neuropatia de fibra. Outras causas desta condi\u00e7\u00e3o incluem uma doen\u00e7a metab\u00f3lica chamada doen\u00e7a de Fabry, dist\u00farbios imunol\u00f3gicos como doen\u00e7a cel\u00edaca ou s\u00edndrome de Sjogren, uma condi\u00e7\u00e3o inflamat\u00f3ria chamada sarcoidose, e infec\u00e7\u00e3o pelo v\u00edrus da imunodefici\u00eancia humana (VIH)."
    },
    {
        "qid":"0000918-4",
        "qtype":"inheritance",
        "question":"A neuropatia por fibras pequenas \u00e9 herdada?",
        "answer":"A neuropatia por fibras pequenas \u00e9 herdada em um padr\u00e3o autoss\u00f4mico dominante, o que significa que uma c\u00f3pia do gene alterado SCN9A ou gene SCN10A em cada c\u00e9lula \u00e9 suficiente para causar o dist\u00farbio. Em alguns casos, uma pessoa afetada herda a muta\u00e7\u00e3o de um pai afetado. Outros casos resultam de novas muta\u00e7\u00f5es no gene e ocorrem em pessoas sem hist\u00f3rico do dist\u00farbio em sua fam\u00edlia. Quando a causa gen\u00e9tica da neuropatia por fibras pequenas \u00e9 desconhecida ou quando a doen\u00e7a \u00e9 causada por outra desordem, o padr\u00e3o de heran\u00e7a n\u00e3o est\u00e1 claro."
    },
    {
        "qid":"0000918-5",
        "qtype":"treatment",
        "question":"Quais s\u00e3o os tratamentos para a neuropatia por fibras pequenas?",
        "answer":"Esses recursos abordam o diagn\u00f3stico ou o manejo da neuropatia por fibras pequenas: - Registro de Testes Gen\u00e9ticos: Neuropatia por fibras pequenas Estes recursos de MedlinePlus oferecem informa\u00e7\u00f5es sobre o diagn\u00f3stico e o manejo de v\u00e1rias condi\u00e7\u00f5es de sa\u00fade: - Testes Diagn\u00f3sticos - Terapia medicamentosa - Cirurgia e Reabilita\u00e7\u00e3o - Aconselhamento Gen\u00e9tico - Cuidados Paliativos"
    }
]