[
    {
        "qid":"0000075-1",
        "qtype":"information",
        "question":"O que \u00e9 a s\u00edndrome de Asperger?",
        "answer":"A s\u00edndrome de Asperger \u00e9 um dist\u00farbio no espectro do autismo, que \u00e9 um grupo de condi\u00e7\u00f5es caracterizadas por comunica\u00e7\u00e3o prejudicada e intera\u00e7\u00e3o social. A s\u00edndrome de Asperger est\u00e1 no fim do espectro do autismo. Muitos indiv\u00edduos afetados aprendem a compensar suas diferen\u00e7as e a viver vidas independentes e bem sucedidas. No entanto, os desafios comportamentais associados a essa condi\u00e7\u00e3o muitas vezes levam ao isolamento social e dificuldades na escola, no trabalho e nas rela\u00e7\u00f5es pessoais. Pessoas com s\u00edndrome de Asperger t\u00eam intelig\u00eancia m\u00e9dia ou superior \u00e0 m\u00e9dia. Ao contr\u00e1rio das pessoas com outros dist\u00farbios no espectro autista, eles n\u00e3o s\u00e3o atrasados no seu desenvolvimento lingu\u00edstico. No entanto, sua capacidade de manter uma conversa muitas vezes \u00e9 prejudicada por uma tend\u00eancia a tomar express\u00f5es ou declara\u00e7\u00f5es humor\u00edsticas literalmente e uma incapacidade de ler sinais n\u00e3o verbais como linguagem corporal para entender o que os outros est\u00e3o sentindo. Eles podem falar em uma voz monotone, ter manierismos incomuns, ou escolher t\u00f3picos incomuns de conversa. Indiv\u00edduos com s\u00edndrome de Asperger tendem a desenvolver um intenso interesse em um determinado assunto. Esse interesse pode ser um hobby tradicional ou disciplina acad\u00eamica, e muitas pessoas com s\u00edndrome de Asperger desenvolvem habilidades avan\u00e7adas em campos como m\u00fasica, ci\u00eancia, matem\u00e1tica, ou programa\u00e7\u00e3o de computador. No entanto, eles tamb\u00e9m podem focar em um interesse incomum como rotas de \u00f4nibus ou um tipo particular de aparelho dom\u00e9stico. Muitas vezes eles s\u00e3o capazes de lembrar enormes quantidades de detalhes sobre seu assunto de interesse. Eles podem querer compartilhar essa grande quantidade de informa\u00e7\u00e3o com outros e podem resistir \u00e0 divers\u00e3o para outros t\u00f3picos. Pessoas com s\u00edndrome de Asperger tendem a ser r\u00edgidas sobre suas rotinas estabelecidas e podem resistir fortemente a interrup\u00e7\u00f5es como mudan\u00e7as na agenda. Tamb\u00e9m podem ter dificuldade em tolerar est\u00edmulos sensoriais como ru\u00eddo ou luzes. Outras caracter\u00edsticas da s\u00edndrome de Asperger podem incluir leve comprometimento das habilidades motoras. Por exemplo, habilidades b\u00e1sicas como rastejar e caminhar podem ser um pouco atrasadas. Indiv\u00edduos afetados tamb\u00e9m podem ter problemas de coordena\u00e7\u00e3o que prejudicam sua capacidade de se envolver em atividades como jogar bolas ou andar de bicicleta. Esta falta f\u00edsica pode levar a um maior isolamento social de crian\u00e7as com s\u00edndrome de Asperger. Sinais e sintomas da s\u00edndrome de Asperger podem se tornar evidentes aos 3 anos de idade, quando a maioria das crian\u00e7as come\u00e7a a desenvolver habilidades sociais, como aprender a brincar com outros. Algumas crian\u00e7as afetadas podem chegar \u00e0 aten\u00e7\u00e3o m\u00e9dica devido a atrasos motoristas. Na maioria dos casos, crian\u00e7as com s\u00edndrome de Asperger s\u00e3o diagnosticadas durante os anos de ensino fundamental, como seu comportamento social continua a divergir do caminho de desenvolvimento t\u00edpico. Dificuldades com habilidades sociais geralmente continuam at\u00e9 a idade adulta, e indiv\u00edduos afetados est\u00e3o em risco aumentado de outros dist\u00farbios comportamentais ou psiqui\u00e1tricos, como d\u00e9ficit de aten\u00e7\u00e3o-hiperatividade dist\u00farbio (TDAH), depress\u00e3o, ansiedade, e dist\u00farbio obsessivo-compulsivo."
    },
    {
        "qid":"0000075-2",
        "qtype":"frequency",
        "question":"Quantas pessoas s\u00e3o afetadas pela s\u00edndrome de Asperger?",
        "answer":"A preval\u00eancia da s\u00edndrome de Asperger n\u00e3o est\u00e1 bem estabelecida. Estimativas variam de 1 em 250 a 1 em 5.000 crian\u00e7as. Tr\u00eas a quatro vezes mais machos s\u00e3o afetados do que f\u00eameas. Devido \u00e0s mudan\u00e7as na forma como os dist\u00farbios do desenvolvimento s\u00e3o classificados, a s\u00edndrome de Asperger n\u00e3o foi frequentemente diagnosticada em adultos at\u00e9 recentemente, e a preval\u00eancia \u00e9 frequentemente percebida como aumentando conforme mais pessoas s\u00e3o reconhecidas como tendo caracter\u00edsticas da condi\u00e7\u00e3o. Muitos indiv\u00edduos ligeiramente afetados provavelmente continuam sem ser diagnosticados."
    },
    {
        "qid":"0000075-3",
        "qtype":"genetic changes",
        "question":"Quais s\u00e3o as altera\u00e7\u00f5es gen\u00e9ticas relacionadas \u00e0 s\u00edndrome de Asperger?",
        "answer":"Enquanto se acredita que fatores gen\u00e9ticos contribuem para o desenvolvimento da s\u00edndrome de Asperger, nenhum gene relacionado foi confirmado. N\u00e3o est\u00e1 claro se certas varia\u00e7\u00f5es g\u00eanicas que est\u00e3o sendo estudadas em outros dist\u00farbios do espectro do autismo desempenhar\u00e3o um papel na s\u00edndrome de Asperger. Parece prov\u00e1vel que uma combina\u00e7\u00e3o de varia\u00e7\u00f5es gen\u00e9ticas e fatores ambientais influenciem o desenvolvimento dessa condi\u00e7\u00e3o complexa. A s\u00edndrome de Asperger \u00e9 uma desordem do desenvolvimento cerebral. Pesquisadores identificaram diferen\u00e7as na estrutura e fun\u00e7\u00e3o de regi\u00f5es espec\u00edficas do c\u00e9rebro entre crian\u00e7as com s\u00edndrome de Asperger e crian\u00e7as n\u00e3o afetadas. Essas diferen\u00e7as provavelmente surgem durante o desenvolvimento antes do nascimento, quando as c\u00e9lulas do c\u00e9rebro est\u00e3o migrando para seus lugares apropriados. As diferen\u00e7as no desenvolvimento cerebral que ocorrem na s\u00edndrome de Asperger parecem afetar \u00e1reas do c\u00e9rebro envolvidas no pensamento, comportamento e emo\u00e7\u00f5es, como o c\u00f3rtex pr\u00e9-frontal, a am\u00edgdala e a \u00e1rea do rosto fusiforme. Em particular, fun\u00e7\u00f5es cognitivas chamadas teoria da mente, coer\u00eancia central e fun\u00e7\u00e3o executiva s\u00e3o afetadas. Teoria da mente \u00e9 a habilidade de entender que outras pessoas t\u00eam suas pr\u00f3prias id\u00e9ias, emo\u00e7\u00f5es e percep\u00e7\u00f5es, e de empatizar com elas. Est\u00e1 relacionado ao funcionamento correto de um mecanismo cerebral chamado sistema de neur\u00f4nios espelhos, que normalmente \u00e9 ativo tanto quando certas a\u00e7\u00f5es s\u00e3o realizadas como quando outras s\u00e3o observadas realizando as mesmas a\u00e7\u00f5es. Pesquisadores acreditam que o sistema de neur\u00f4nios espelhos \u00e9 prejudicado em pessoas com s\u00edndrome de Asperger. A coer\u00eancia central \u00e9 a capacidade de integrar percep\u00e7\u00f5es individuais em um contexto maior, comumente conhecido como \"ver o quadro geral\". Por exemplo, uma pessoa com s\u00edndrome de Asperger pode ser capaz de descrever \u00e1rvores individuais em grande detalhe sem reconhecer que eles s\u00e3o parte de uma floresta. Fun\u00e7\u00e3o executiva \u00e9 a capacidade de planejar e implementar a\u00e7\u00f5es e desenvolver estrat\u00e9gias de resolu\u00e7\u00e3o de problemas. Essa fun\u00e7\u00e3o inclui habilidades como controle de impulsos, automonitoramento, focaliza\u00e7\u00e3o da aten\u00e7\u00e3o adequada e flexibilidade cognitiva. Pessoas com d\u00e9ficit nessas habilidades podem ter dificuldade em algumas atividades de vida di\u00e1ria e em intera\u00e7\u00f5es sociais. Acredita-se que as diferen\u00e7as no funcionamento cognitivo observadas em pessoas com s\u00edndrome de Asperger d\u00e3o origem aos padr\u00f5es comportamentais caracter\u00edsticos dessa condi\u00e7\u00e3o."
    },
    {
        "qid":"0000075-4",
        "qtype":"inheritance",
        "question":"A s\u00edndrome de Asperger \u00e9 herdada?",
        "answer":"Os dist\u00farbios do espectro autista, incluindo a s\u00edndrome de Asperger, t\u00eam tend\u00eancia a correr em fam\u00edlias, mas o padr\u00e3o de heran\u00e7a \u00e9 desconhecido."
    },
    {
        "qid":"0000075-5",
        "qtype":"treatment",
        "question":"Quais s\u00e3o os tratamentos para a s\u00edndrome de Asperger?",
        "answer":"Esses recursos abordam o diagn\u00f3stico ou manejo da s\u00edndrome de Asperger: - Registro de Testes Gen\u00e9ticos: S\u00edndrome de Asperger 1 - Registro de Testes Gen\u00e9ticos: S\u00edndrome de Asperger 2 - Registro de Testes Gen\u00e9ticos: S\u00edndrome de Asperger 3 - Registro de Testes Gen\u00e9ticos: S\u00edndrome de Asperger 4 - Registro de Testes Gen\u00e9ticos: S\u00edndrome de Asperger X-linked 1 - Registro de Testes Gen\u00e9ticos: S\u00edndrome de Asperger X-linked 2 - Registro de Testes Gen\u00e9ticos: Dist\u00farbio de Asperger - MedlinePlus Encyclopedia: S\u00edndrome de Asperger - Instituto Nacional de Sa\u00fade Mental: Como o ASD \u00e9 tratado? Esses recursos de MedlinePlus oferecem informa\u00e7\u00f5es sobre o diagn\u00f3stico e o manejo de v\u00e1rias condi\u00e7\u00f5es de sa\u00fade: - Testes Diagn\u00f3sticos - Terapia de Medicamentos - Cirurgia e Reabilita\u00e7\u00e3o - Aconselhamento Gen\u00e9tico - Cuidados Paliativos"
    }
]