[
    {
        "qid":"0002792-1",
        "qtype":"information",
        "question":"O que \u00e9 a s\u00edndrome de choque hemorr\u00e1gico e encefalopatia?",
        "answer":"A s\u00edndrome de choque hemorr\u00e1gico e encefalopatia (SHES) \u00e9 uma doen\u00e7a rara que ocorre de repente em crian\u00e7as previamente saud\u00e1veis. Esta condi\u00e7\u00e3o \u00e9 caracterizada por choque grave, coagulopatia, encefalopatia e disfun\u00e7\u00e3o hep\u00e1tica e renal. A maioria dos casos de HSES ocorre em crian\u00e7as de 3 a 8 meses, embora tamb\u00e9m possa ocorrer em crian\u00e7as mais velhas. Indiv\u00edduos com HSES t\u00eam temperaturas corporais extremamente altas e falhas m\u00faltiplas de \u00f3rg\u00e3os. Essa condi\u00e7\u00e3o muitas vezes causa problemas neurol\u00f3gicos a longo prazo ou morte. A causa do HSES \u00e9 desconhecida."
    },
    {
        "qid":"0002792-2",
        "qtype":"causes",
        "question":"O que causa a s\u00edndrome de choque hemorr\u00e1gico e encefalopatia?",
        "answer":"O que causa choque hemorr\u00e1gico e s\u00edndrome de encefalopatia? A causa do choque hemorr\u00e1gico e da s\u00edndrome da encefalopatia \u00e9 desconhecida. Alguns pesquisadores acreditam que essa condi\u00e7\u00e3o \u00e9 causada por uma complexa combina\u00e7\u00e3o de fatores gen\u00e9ticos e ambientais. Pesquisadores propuseram v\u00e1rios fatores que podem contribuir para o desenvolvimento desta condi\u00e7\u00e3o, incluindo infec\u00e7\u00e3o, exposi\u00e7\u00e3o a toxinas no ambiente, e sobreembrulhamento de beb\u00eas com febre. O choque hemorr\u00e1gico e a s\u00edndrome da encefalopatia n\u00e3o foram relatados como sendo associados a um grupo \u00e9tnico espec\u00edfico ou origem religiosa."
    }
]