[
    {
        "qid":"0004291-1",
        "qtype":"information",
        "question":"E se o c\u00e2ncer voltar? N\u00e3o, n\u00e3o, n\u00e3o, n\u00e3o, n\u00e3o, n\u00e3o, n\u00e3o, n\u00e3o, n\u00e3o, n\u00e3o, n\u00e3o, n\u00e3o, n\u00e3o, n\u00e3o, n\u00e3o, n\u00e3o, n\u00e3o, n\u00e3o, n\u00e3o, n\u00e3o, n\u00e3o, n\u00e3o, n\u00e3o, n\u00e3o, n\u00e3o, n\u00e3o, n\u00e3o, n\u00e3o, n\u00e3o, n\u00e3o, n\u00e3o, n\u00e3o, n\u00e3o, n\u00e3o, n\u00e3o, n\u00e3o, n\u00e3o, n\u00e3o, n\u00e3o, n\u00e3o, n\u00e3o, n\u00e3o, n\u00e3o, n\u00e3o.",
        "answer":""
    },
    {
        "qid":"0004291-3",
        "qtype":"susceptibility",
        "question":"Quem est\u00e1 em risco e se o c\u00e2ncer voltar? N\u00e3o, n\u00e3o, n\u00e3o, n\u00e3o, n\u00e3o, n\u00e3o, n\u00e3o, n\u00e3o, n\u00e3o, n\u00e3o, n\u00e3o, n\u00e3o, n\u00e3o, n\u00e3o, n\u00e3o, n\u00e3o, n\u00e3o, n\u00e3o, n\u00e3o, n\u00e3o, n\u00e3o, n\u00e3o, n\u00e3o, n\u00e3o, n\u00e3o, n\u00e3o, n\u00e3o, n\u00e3o, n\u00e3o, n\u00e3o, n\u00e3o, n\u00e3o, n\u00e3o, n\u00e3o, n\u00e3o, n\u00e3o, n\u00e3o, n\u00e3o, n\u00e3o, n\u00e3o, n\u00e3o, n\u00e3o, n\u00e3o, n\u00e3o.",
        "answer":""
    }
]